generator/__init__.py
generator/cli.py
generator/filters.py
generator/fingerprint.py
generator/generation.py
generator/intermediates.py
generator/scoring.py
generator/visualization.py
intermediate_generator-0.1.0.dist-info/LICENSE
intermediate_generator-0.1.0.dist-info/METADATA
intermediate_generator-0.1.0.dist-info/WHEEL
intermediate_generator-0.1.0.dist-info/entry_points.txt
intermediate_generator-0.1.0.dist-info/top_level.txt
intermediate_generator-0.1.0.dist-info/RECORD
